Workbook
Name Aporte: Simulador!$D$18
Name patrimonio_acumulado: Simulador!$D$21
Name qtde_anos: Simulador!$D$19
Name rendimento_carteira: Simulador!$D$13
Name salario: Simulador!$D$12
Name sugestao_investiment: Simulador!$D$14
Name Taxa_mensal: Simulador!$D$20

Sheet Simulador
B11: CONFIGURAÇÕES
B12: Salário | D12: 4000
B13: Rendimento carteira | D13: 0.0093
B14: Sugestão de Investimento | D14: =D12*30% -> 1200
B17: INVESTIMENTO MENSAL
B18: Valor investido por mês? | D18: 600
B19: Por quantos anos? | D19: 5
B20: Taxa de rendimento mensal? | D20: 0.0179
A21: 2 | B21: Patrimônio acumulado | D21: =FV(Taxa_mensal,qtde_anos*12,Aporte*-1) -> 63666.754
A22: 10 | B22: Dividendos mensais | D22: =patrimonio_acumulado*rendimento_carteira -> 592.10082
A23: 15
A24: 20
A25: 30 | B25: CENÁRIOS | D25: Dividendo
B26: Quanto em 2 anos? | C26: =FV(Taxa_mensal,$A21*12,Aporte*-1) -> 17792.686 | D26: =C26*rendimento_carteira -> 165.47198
B27: Quanto em 10 anos? | C27: =FV(Taxa_mensal,$A22*12,Aporte*-1) -> 248261.6 | D27: =C27*rendimento_carteira -> 2308.8329
B28: Quanto em 15 anos? | C28: =FV(Taxa_mensal,$A23*12,Aporte*-1) -> 783474.33 | D28: =C28*rendimento_carteira -> 7286.3113
B29: Quanto em 20 anos? | C29: =FV(Taxa_mensal,$A24*12,Aporte*-1) -> 2335265.6 | D29: =C29*rendimento_carteira -> 21717.97
B30: Quanto em 30 anos? | C30: =FV(Taxa_mensal,$A25*12,Aporte*-1) -> 19879604 | D30: =C30*rendimento_carteira -> 184880.32
B33: PERFIL | C33: MODERADO
B34: Valor a ser investido por mês | C34: 600
B36: Tipo de FII | C36: Percentual Sugerido | D36: Valor
B37: Papel | C37: =VLOOKUP($C$33&"-"&B37,Planilha1!$A:$D,4,0) -> 0.32 | D37: =$C$34*C37 -> 192
B38: Tijolo | C38: =VLOOKUP($C$33&"-"&B38,Planilha1!$A:$D,4,0) -> 0.4 | D38: =$C$34*C38 -> 240
B39: Hibridos | C39: =VLOOKUP($C$33&"-"&B39,Planilha1!$A:$D,4,0) -> 0.08 | D39: =$C$34*C39 -> 48
B40: Fof's | C40: =VLOOKUP($C$33&"-"&B40,Planilha1!$A:$D,4,0) -> 0.1 | D40: =$C$34*C40 -> 60
B41: Desenvolvimento | C41: =VLOOKUP($C$33&"-"&B41,Planilha1!$A:$D,4,0) -> 0.1 | D41: =$C$34*C41 -> 60
B42: Hotelarias | C42: =VLOOKUP($C$33&"-"&B42,Planilha1!$A:$D,4,0) -> 0 | D42: =$C$34*C42 -> 0
B43: Total | D43: =SUM(D37:D42) -> 600

Sheet Planilha1
A2: CHAVE | B2: PERFIL | C2: TIPO DE FII | D2: %
A3: =B3&"-"&C3 -> CONSERVADOR-Papel | B3: CONSERVADOR | C3: Papel | D3: 0.3
A4: =B4&"-"&C4 -> CONSERVADOR-Tijolo | B4: CONSERVADOR | C4: Tijolo | D4: 0.5 | G4: CONSERVADOR-Papel | H4: =VLOOKUP(G4,A:D,4,0) -> 0.3
A5: =B5&"-"&C5 -> CONSERVADOR-Hibridos | B5: CONSERVADOR | C5: Hibridos | D5: 0.1
A6: =B6&"-"&C6 -> CONSERVADOR-Fof's | B6: CONSERVADOR | C6: Fof's | D6: 0.1
A7: =B7&"-"&C7 -> CONSERVADOR-Desenvolvimento | B7: CONSERVADOR | C7: Desenvolvimento | D7: 0
A8: =B8&"-"&C8 -> CONSERVADOR-Hotelarias | B8: CONSERVADOR | C8: Hotelarias | D8: 0
A9: =B9&"-"&C9 -> MODERADO-Papel | B9: MODERADO | C9: Papel | D9: 0.32
A10: =B10&"-"&C10 -> MODERADO-Tijolo | B10: MODERADO | C10: Tijolo | D10: 0.4
A11: =B11&"-"&C11 -> MODERADO-Hibridos | B11: MODERADO | C11: Hibridos | D11: 0.08
A12: =B12&"-"&C12 -> MODERADO-Fof's | B12: MODERADO | C12: Fof's | D12: 0.1
A13: =B13&"-"&C13 -> MODERADO-Desenvolvimento | B13: MODERADO | C13: Desenvolvimento | D13: 0.1
A14: =B14&"-"&C14 -> MODERADO-Hotelarias | B14: MODERADO | C14: Hotelarias | D14: 0
A15: =B15&"-"&C15 -> AGRESSIVO-Papel | B15: AGRESSIVO | C15: Papel | D15: 0.5
A16: =B16&"-"&C16 -> AGRESSIVO-Tijolo | B16: AGRESSIVO | C16: Tijolo | D16: 0.1
... A20: =B20&"-"&C20 -> AGRESSIVO-Hotelarias | B20: AGRESSIVO | C20: Hotelarias | D20: 0.1
